MANIFEST.in
setup.py
version.py
src/toil_lib/__init__.py
src/toil_lib/files.py
src/toil_lib/jobs.py
src/toil_lib/programs.py
src/toil_lib/urls.py
src/toil_lib.egg-info/PKG-INFO
src/toil_lib.egg-info/SOURCES.txt
src/toil_lib.egg-info/dependency_links.txt
src/toil_lib.egg-info/top_level.txt
src/toil_lib/test/__init__.py
src/toil_lib/test/test_files.py
src/toil_lib/test/test_jobs.py
src/toil_lib/test/test_lib.py
src/toil_lib/test/test_programs.py
src/toil_lib/test/test_urls.py
src/toil_lib/tools/QC.py
src/toil_lib/tools/__init__.py
src/toil_lib/tools/aligners.py
src/toil_lib/tools/indexing.py
src/toil_lib/tools/mutation_callers.py
src/toil_lib/tools/preprocessing.py
src/toil_lib/tools/quantifiers.py
src/toil_lib/tools/spark_tools.py
src/toil_lib/tools/variant_annotation.py
src/toil_lib/tools/variant_manipulation.py