Metadata-Version: 1.0
Name: toil-lib
Version: 1.1.1
Summary: A common library for functions and tools used in toil-based pipelines
Home-page: https://github.com/BD2KGenomics/toil-lib
Author: UCSC Computational Genomics Lab
Author-email: cgl-toil@googlegroups.com
License: UNKNOWN
Platform: UNKNOWN
